[
    {
        "title": "Conoce la oferta educativa en todo el Perú",
        "description": "Consulta información sobre colegios, institutos y universidades.",
        "link": "https://www.minedu.gob.pe/oferta-educativa/",
        "date": "2024-11-05"
    },
    {
        "title": "Calendario Escolar 2024",
        "description": "Infórmate sobre las dates del calendario escolar para el próximo año.",
        "link": "https://www.minedu.gob.pe/calendario-escolar/",
        "date": "05-11-2024"
    },
    {
        "title": "Becas y Créditos Educativos",
        "description": "Accede a oportunidades de financiamiento para tu educación.",
        "link": "https://www.minedu.gob.pe/becas/",
        "date": "06-11-2024"
        
    },
    {
        "title": "Conoce la oferta educativa en todo el Perú",
        "description": "Consulta información sobre colegios, institutos y universidades.",
        "link": "https://www.minedu.gob.pe/oferta-educativa/",
        "date": "06-11-2024"
    },
    {
        "title": "Calendario Escolar 2024",
        "description": "Infórmate sobre las dates del calendario escolar para el próximo año.",
        "link": "https://www.minedu.gob.pe/calendario-escolar/",
        "date": "07-11-2024"
    },
    {
        "title": "Becas y Créditos Educativos",
        "description": "Accede a oportunidades de financiamiento para tu educación.",
        "link": "https://www.minedu.gob.pe/becas/",
        "date": "07-11-2024"
    },
    {
        "title": "Conoce la oferta educativa en todo el Perú",
        "description": "Consulta información sobre colegios, institutos y universidades.",
        "link": "https://www.minedu.gob.pe/oferta-educativa/",
        "date": "07-11-2024"
    },
    {
        "title": "Calendario Escolar 2024",
        "description": "Infórmate sobre las dates del calendario escolar para el próximo año.",
        "link": "https://www.minedu.gob.pe/calendario-escolar/",
        "date": "08-11-2024"
    },
    {
        "title": "Becas y Créditos Educativos",
        "description": "Accede a oportunidades de financiamiento para tu educación.",
        "link": "https://www.minedu.gob.pe/becas/",
        "date": "08-11-2024"
    },
    {
        "title": "Guillermo y su educación",
        "description": "Accede a oportunidades de financiamiento para tu educación.",
        "link": "https://www.minedu.gob.pe/becas/",
        "date": "08-11-2024"
    }
    


    








]
